setup.py
nullpobug.chaser.egg-info/PKG-INFO
nullpobug.chaser.egg-info/SOURCES.txt
nullpobug.chaser.egg-info/dependency_links.txt
nullpobug.chaser.egg-info/top_level.txt
nullpochaser/__init__.py
nullpochaser/connection.py
nullpochaser/const.py
nullpochaser/main.py
nullpochaser/maps.py
nullpochaser/utils.py
nullpochaser/chasers/__init__.py
nullpochaser/chasers/active.py
nullpochaser/chasers/base.py
nullpochaser/chasers/silent.py