Metadata-Version: 1.1
Name: nullpobug.chaser
Version: 0.1
Summary: CHaser 2012 client library for Python
Home-page: UNKNOWN
Author: Shinya Okano
Author-email: UNKNOWN
License: UNKNOWN
Platform: UNKNOWN
Classifier: Programming Language :: Python :: 2.7
